kronicle/__init__.py
kronicle/main.py
kronicle/api/routes/health_check.py
kronicle/api/routes/read_routes.py
kronicle/api/routes/setup_routes.py
kronicle/api/routes/shared_read_routes.py
kronicle/api/routes/shared_write_routes.py
kronicle/api/routes/write_routes.py
kronicle/controller/db_wrapper.py
kronicle/controller/input_payloads.py
kronicle/controller/operation_gate.py
kronicle/controller/processed_payload.py
kronicle/controller/response_payload.py
kronicle/core/deps.py
kronicle/core/ini_settings.py
kronicle/core/security.py
kronicle/db/channel_metadata.py
kronicle/db/channel_schema.py
kronicle/db/db_manager.py
kronicle/errors/error_types.py
kronicle/errors/exception_handlers.py
kronicle/log_bus/event_bus.py
kronicle/log_bus/http_reply.py
kronicle/log_bus/log_consumers.py
kronicle/log_bus/log_event.py
kronicle/log_bus/log_publisher.py
kronicle/log_bus/mid_auth.py
kronicle/log_bus/mid_sanitize.py
kronicle/logging/log_consumer.py
kronicle/logging/log_event.py
kronicle/logging/log_producer.py
kronicle/types/const.py
kronicle/types/iso_datetime.py
kronicle/types/query_params.py
kronicle/types/schema_types.py
kronicle/utils/dev_logs.py
kronicle/utils/dict_utils.py
kronicle/utils/file_utils.py
kronicle/utils/str_utils.py
kronicle-0.1.0.dist-info/licenses/LICENCE.md
kronicle-0.1.0.dist-info/METADATA
kronicle-0.1.0.dist-info/WHEEL
kronicle-0.1.0.dist-info/top_level.txt
kronicle-0.1.0.dist-info/RECORD
