Metadata-Version: 2.4
Name: kronicle
Version: 0.1.0
Summary: FastAPI-powered TimescaleDB microservice for storing time-series measurements
Author-email: Olivier Martineau <olivier.martineau@irisa.fr>
Maintainer-email: Olivier Martineau <olivier.martineau@irisa.fr>
License-Expression: AGPL-3.0
Project-URL: Homepage, https://github.com/logistica-dev/kronicle
Project-URL: Documentation, https://github.com/logistica-dev/kronicle/blob/latest_branch/README.md
Project-URL: Repository, https://github.com/logistica-dev/kronicle
Keywords: timeseries,timescaledb,storage,fastapi,digital twin,Univ. Rennes,IRISA
Classifier: Programming Language :: Python :: 3.11
Classifier: Programming Language :: Python :: 3.12
Classifier: Programming Language :: Python :: 3.13
Classifier: Natural Language :: English
Classifier: Operating System :: OS Independent
Requires-Python: >=3.11
License-File: LICENCE.md
Requires-Dist: asyncpg==0.30.0
Requires-Dist: cryptography==46.0.3
Requires-Dist: fastapi==0.119.0
Requires-Dist: python-jose==3.5.0
Requires-Dist: passlib==1.7.4
Requires-Dist: pydantic==2.12.2
Requires-Dist: pydantic_core==2.41.4
Requires-Dist: rich==14.2.0
Requires-Dist: secure==1.0.1
Requires-Dist: starlette==0.48.0
Requires-Dist: uvicorn==0.38.0
Provides-Extra: dev
Requires-Dist: black; extra == "dev"
Requires-Dist: nbstripout; extra == "dev"
Requires-Dist: pip-upgrade-outdated; extra == "dev"
Requires-Dist: pre-commit; extra == "dev"
Requires-Dist: ruff; extra == "dev"
Dynamic: license-file
